unumpy/__init__.py
unumpy/_multimethods.py
unumpy/_version.py
unumpy/cupy_backend.py
unumpy/dask_backend.py
unumpy/numpy_backend.py
unumpy/sparse_backend.py
unumpy/torch_backend.py
unumpy/xnd_backend.py
unumpy/tests/__init__.py
unumpy/tests/test_numpy.py
unumpy-0.6.1.dist-info/LICENSE
unumpy-0.6.1.dist-info/METADATA
unumpy-0.6.1.dist-info/WHEEL
unumpy-0.6.1.dist-info/top_level.txt
unumpy-0.6.1.dist-info/RECORD
