Metadata-Version: 2.1
Name: unumpy
Version: 0.6.1
Summary: Array interface object for Python with pluggable backends and a multiple-dispatchmechanism for defining down-stream functions
Home-page: https://github.com/Quansight-Labs/uarray/
Maintainer: Hameer Abbasi
Maintainer-email: habbasi@quansight.com
License: BSD 3-Clause License (Revised)
Project-URL: Documentation, https://unumpy.uarray.org/
Project-URL: Source, https://github.com/Quansight-Labs/uarray/
Project-URL: Tracker, https://github.com/Quansight-Labs/uarray/issues
Keywords: uarray,numpy,scipy,pytorch,cupy,tensorflow
Platform: UNKNOWN
Classifier: Development Status :: 2 - Pre-Alpha
Classifier: Operating System :: OS Independent
Classifier: License :: OSI Approved :: BSD License
Classifier: Programming Language :: Python
Classifier: Programming Language :: Python :: 3
Classifier: Programming Language :: Python :: 3.5
Classifier: Programming Language :: Python :: 3.6
Classifier: Programming Language :: Python :: 3.7
Classifier: Programming Language :: Python :: 3 :: Only
Classifier: Intended Audience :: Developers
Classifier: Intended Audience :: Science/Research
Requires-Python: >=3.5, <4
Requires-Dist: uarray (==0.6)
Provides-Extra: all
Provides-Extra: backends
Provides-Extra: docs
Provides-Extra: optional
Provides-Extra: tests
